{
    "header_text": "Pidiendo dinero",
    "header_icon": "assets/subtitle.png",
    "elements": [
        {
            "type": "Text",
            "text": "Has tenido algunos problemas financieros recientemente. Para llegar a fin de mes, necesitas pedir un préstamo a un familiar. Piensas que esto es... "
        },
        {
            "type": "Entry",
            "name": "Pidiendo dinero_Finanzas_entry1"
        }
    ],
    "navigation_conditions": "wait_for_correct",
    "type": "positive",
    "scenario_num": 7
}