{
    "header_text": "En un barco",
    "header_icon": "assets/subtitle.png",
    "elements": [
        {
            "type": "Text",
            "text": "La sensación en tus piernas probablemente....."
        },
        {
            "type": "WordPuzzle",
            "name": "En un barco_Situaciones Sociales_puzzle_word2",
            "correct_feedback": "Correcto!",
            "incorrect_feedback": "¡Vaya! Eso no parece correcto. Por favor, espere un momento y intenta de nuevo.",
            "incorrect_delay": 5000,
            "display_delay": 2000,
            "words": [
                "es"
            ],
            "missing_letter_count": 2
        }
    ],
    "navigation_conditions": "wait_for_correct",
    "type": "positive",
    "scenario_num": 0
}