{
    "header_text": "Compartir con alguien nuevo",
    "header_icon": "assets/subtitle.png",
    "elements": [
        {
            "type": "Text",
            "text": "Compartir con alguien nuevo"
        },
        {
            "type": "Media",
            "url": "./images/468.jpg"
        }
    ],
    "type": "resilience/negation",
    "scenario_num": 9,
    "information": {
        "elements": [
            {
                "type": "text",
                "text": "Al igual que con cualquier habilidad nueva, la práctica constante te ayudará a pensar de manera más flexible."
            }
        ],
        "position": "before",
        "information_count": 1
    }
}